openstack_opentracing/__init__.py
openstack_opentracing/eventlet_tracer.py
openstack_opentracing/jaeger_middleware.py
openstack_opentracing/memcache_tracer.py
openstack_opentracing/remote_sampler.py
openstack_opentracing/tracer_factory.py
openstack_opentracing/test/__init__.py
openstack_opentracing/test/server1.py
openstack_opentracing/test/server2.py
openstack_opentracing/test/server3.py
openstack_opentracing/test/test_middleware.py
openstack_opentracing/test/test_server.py
openstack_opentracing/test/test_wsgi.py
openstack_opentracing-0.0.1.dist-info/METADATA
openstack_opentracing-0.0.1.dist-info/RECORD
openstack_opentracing-0.0.1.dist-info/WHEEL
openstack_opentracing-0.0.1.dist-info/top_level.txt
